{
    "example_source": [
        "▁我还",
        "澄清",
        "了",
        "在该",
        "会议上",
        "提出的",
        "若干",
        "事项",
        "。"
    ],
    "example_target": [
        "<s>",
        "▁i",
        "▁was",
        "▁able",
        "▁to",
        "▁provide",
        "▁clarification",
        "▁on",
        "▁some",
        "▁of",
        "▁the",
        "▁matters",
        "▁which",
        "▁were",
        "▁raised",
        "▁at",
        "▁that",
        "▁meeting",
        ".",
        "</s>"
    ],
    "hypotheses": [
        {
            "hypothesis": [
                "▁i",
                "▁also",
                "▁clarify",
                "▁the",
                "▁number",
                "▁of",
                "▁matters",
                "▁raised",
                "▁by",
                "▁the",
                "▁meeting",
                "."
            ],
            "score": -6.949248790740967
        },
        {
            "hypothesis": [
                "▁i",
                "▁also",
                "▁clarify",
                "▁the",
                "▁number",
                "▁of",
                "▁matters",
                "▁at",
                "▁the",
                "▁meeting",
                "."
            ],
            "score": -7.047731876373291
        },
        {
            "hypothesis": [
                "▁i",
                "▁also",
                "▁clarify",
                "▁the",
                "▁number",
                "▁of",
                "▁matters",
                "▁raised",
                "▁by",
                "▁the",
                "▁conference",
                "."
            ],
            "score": -7.161920547485352
        },
        {
            "hypothesis": [
                "▁i",
                "▁also",
                "▁clarify",
                "▁the",
                "▁number",
                "▁of",
                "▁matters",
                "▁at",
                "▁the",
                "▁conference",
                "."
            ],
            "score": -7.356729984283447
        },
        {
            "hypothesis": [
                "▁i",
                "▁also",
                "▁clarify",
                "▁the",
                "▁number",
                "▁of",
                "▁matters",
                "▁raised",
                "▁at",
                "▁the",
                "▁meeting",
                "."
            ],
            "score": -7.448853015899658
        },
        {
            "hypothesis": [
                "▁i",
                "▁also",
                "▁clarify",
                "▁the",
                "▁number",
                "▁of",
                "▁matters",
                "▁which",
                "▁had",
                "▁been",
                "▁raised",
                "."
            ],
            "score": -8.286876678466797
        },
        {
            "hypothesis": [
                "▁i",
                "▁also",
                "▁clarify",
                "▁that",
                "▁a",
                "▁number",
                "▁of",
                "▁matters",
                "▁had",
                "▁been",
                "▁raised",
                "▁at",
                "▁the",
                "▁meeting",
                "."
            ],
            "score": -9.888864517211914
        },
        {
            "hypothesis": [
                "▁i",
                "▁also",
                "▁clarify",
                "▁the",
                "▁number",
                "▁of",
                "▁matters",
                "▁which",
                "▁had",
                "▁been",
                "▁raised",
                "▁at",
                "▁the",
                "▁meeting",
                "."
            ],
            "score": -10.030364036560059
        },
        {
            "hypothesis": [
                "▁i",
                "▁also",
                "▁clarify",
                "▁that",
                "▁a",
                "▁number",
                "▁of",
                "▁matters",
                "▁had",
                "▁been",
                "▁raised",
                "▁at",
                "▁the",
                "▁conference",
                "."
            ],
            "score": -10.162680625915527
        },
        {
            "hypothesis": [
                "▁i",
                "▁also",
                "▁clarify",
                "▁the",
                "▁number",
                "▁of",
                "▁matters",
                "▁which",
                "▁had",
                "▁been",
                "▁raised",
                "▁at",
                "▁the",
                "▁conference",
                "."
            ],
            "score": -10.289510726928711
        }
    ],
    "diagnostic_info": "eyJ0IjogIjIwMjQtMDYtMzBUMTE6MzY6NTEuMzE5NzMxIiwgImgiOiAiMTkyLjE2OC4yLjEwMyIsICJ1IjogImxlby1sdSJ9"
}